<?xml version="1.0" encoding="UTF-8"?>
<objects serializationModel="Studio.01.10.00">
    <object class="AudioFile" id="{a4381f42-c17f-4b2a-94af-0d5208119ffd}">
        <property name="assetPath">
            <value>Tree Falling.wav</value>
        </property>
        <property name="frequencyInKHz">
            <value>44.0999985</value>
        </property>
        <property name="channelCount">
            <value>2</value>
        </property>
        <property name="length">
            <value>3.5624943310657597</value>
        </property>
        <relationship name="masterAssetFolder">
            <destination>{5a33e275-12ea-4106-a481-cde9e6f7b954}</destination>
        </relationship>
    </object>
</objects>
